{"chunk_definitions":[{"row":11,"row_count":1,"visible":true,"expansion_state":0,"options":{"engine":"r","label":"setup","include":false,"dev":"png"},"document_id":"8D53A47D","chunk_id":"csetup_chunk","chunk_label":"setup"},{"row":22,"row_count":1,"visible":true,"expansion_state":0,"options":{"engine":"r","label":" \"Loading Libraries\"","message":false,"dev":"png"},"document_id":"8D53A47D","chunk_id":"cxoubujdo5a7m","chunk_label":"unnamed-chunk-1"},{"row":26,"row_count":1,"visible":true,"expansion_state":1,"options":{"engine":"r","label":"Loading Data","message":false,"dev":"png"},"document_id":"8D53A47D","chunk_id":"crappilol5msx","chunk_label":"\"Loading Data\""},{"row":49,"row_count":1,"visible":true,"expansion_state":0,"options":{"engine":"r","label":" \"Removing Features\"","dev":"png"},"document_id":"8D53A47D","chunk_id":"cr2ai3mcw0i37","chunk_label":"unnamed-chunk-2"},{"row":57,"row_count":1,"visible":true,"expansion_state":0,"options":{"engine":"r","label":" \"Creating Models\"","dev":"png"},"document_id":"8D53A47D","chunk_id":"c2klu6q5m19wh","chunk_label":"unnamed-chunk-3"},{"row":77,"row_count":1,"visible":true,"expansion_state":0,"options":{"engine":"r","label":"unnamed-chunk-12","dev":"png"},"document_id":"8D53A47D","chunk_id":"coforii1off4n","chunk_label":"unnamed-chunk-4"},{"row":94,"row_count":1,"visible":true,"expansion_state":0,"options":{"engine":"r","label":" \"Performing Manual Backwards Selection on Non-Native Model\"","dev":"png"},"document_id":"8D53A47D","chunk_id":"cv9vts9y94f2r","chunk_label":"unnamed-chunk-5"},{"row":102,"row_count":1,"visible":true,"expansion_state":0,"options":{"engine":"r","label":" \"Determining Fit\"","dev":"png"},"document_id":"8D53A47D","chunk_id":"cebfb7tnumtwq","chunk_label":"unnamed-chunk-6"},{"row":112,"row_count":1,"visible":true,"expansion_state":0,"options":{"engine":"r","label":" \"Determining AIC\"","dev":"png"},"document_id":"8D53A47D","chunk_id":"ca02azhlbfh7e","chunk_label":"unnamed-chunk-7"},{"row":120,"row_count":1,"visible":true,"expansion_state":0,"options":{"engine":"r","label":" \"Performing stepAIC backwards selection\"","dev":"png"},"document_id":"8D53A47D","chunk_id":"ceyxojrgmr3w4","chunk_label":"unnamed-chunk-8"},{"row":136,"row_count":1,"visible":true,"expansion_state":0,"options":{"engine":"r","label":" \"Performing Likelihood Tests\"","dev":"png"},"document_id":"8D53A47D","chunk_id":"cmycqscpf1fe6","chunk_label":"unnamed-chunk-10"},{"row":177,"row_count":1,"visible":true,"expansion_state":0,"options":{"engine":"r","label":" \"Plotting Strength of Predictors for the Native Model\"","dev":"png"},"document_id":"8D53A47D","chunk_id":"ci56c9ggev8b6","chunk_label":"unnamed-chunk-11"},{"row":216,"row_count":1,"visible":true,"expansion_state":0,"options":{"engine":"r","label":" \"Plotting Strength of Predictors for the Non-Native Model\"","width":10,"height":12,"dev":"png"},"document_id":"8D53A47D","chunk_id":"cjiy9x9p1vcuf","chunk_label":"unnamed-chunk-12"},{"row":230,"row_count":1,"visible":true,"expansion_state":0,"options":{"engine":"r","label":"unnamed-chunk-23","dev":"png"},"document_id":"8D53A47D","chunk_id":"cwz9mihb5d6v6","chunk_label":"unnamed-chunk-13"}],"doc_write_time":1731014277,"chunk_rendered_width":700}